MANIFEST.in
README.rst
ansible_windows_compat.pth
setup.py
ansible_windows_compat/__init__.py
ansible_windows_compat/grp.py
ansible_windows_compat/pwd.py
ansible_windows_compat/syslog.py
ansible_windows_compat.egg-info/PKG-INFO
ansible_windows_compat.egg-info/SOURCES.txt
ansible_windows_compat.egg-info/dependency_links.txt
ansible_windows_compat.egg-info/not-zip-safe
ansible_windows_compat.egg-info/pbr.json
ansible_windows_compat.egg-info/top_level.txt