Metadata-Version: 1.1
Name: ansible-windows-compat
Version: 0.1.0
Summary: Compatibility library to run Ansible Python modules on a Windows target.
Home-page: https://github.com/cchurch/ansible-windows-compat
Author: Chris Church
Author-email: chris@ninemoreminutes.com
License: BSD
Keywords: python ansible windows
Platform: UNKNOWN
Classifier: Development Status :: 3 - Alpha
Classifier: Environment :: Win32 (MS Windows)
Classifier: Intended Audience :: System Administrators
Classifier: License :: OSI Approved :: BSD License
Classifier: Operating System :: OS Independent
Classifier: Operating System :: Microsoft :: Windows
Classifier: Programming Language :: Python
Classifier: Programming Language :: Python :: 2.7
Classifier: Topic :: Software Development :: Libraries
